app/__init__.py
app/cli.py
app/config.py
app/core/__init__.py
app/core/alerts.py
app/core/monitor.py
app/core/storage.py
app/core/storage_file.py
app/core/storage_postgres.py
app/db.py
app/models.py
app/monitors/__init__.py
app/monitors/base.py
app/monitors/cpu.py
app/monitors/disk.py
app/monitors/memory.py
app/monitors/ping.py
server_monitoring_made_easy-0.1.3.dist-info/LICENSE.md
server_monitoring_made_easy-0.1.3.dist-info/METADATA
server_monitoring_made_easy-0.1.3.dist-info/WHEEL
server_monitoring_made_easy-0.1.3.dist-info/entry_points.txt
server_monitoring_made_easy-0.1.3.dist-info/RECORD
