Metadata-Version: 2.3
Name: server-monitoring-made-easy
Version: 0.1.3
Summary: Simple and effective server monitoring with easy configuration and multiple notification options
Author: Timothy Bryant
Author-email: timothybryant3@gmail.com
Requires-Python: >=3.9,<4
Classifier: Programming Language :: Python :: 3
Classifier: Programming Language :: Python :: 3.9
Classifier: Programming Language :: Python :: 3.10
Classifier: Programming Language :: Python :: 3.11
Classifier: Programming Language :: Python :: 3.12
Classifier: Programming Language :: Python :: 3.13
Requires-Dist: alembic (>=1.13.1)
Requires-Dist: apprise (>=1.7.1)
Requires-Dist: click (>=8.1.7)
Requires-Dist: prometheus-client (>=0.20.0)
Requires-Dist: psutil (>=5.9.8)
Requires-Dist: psycopg2-binary (>=2.9.9)
Requires-Dist: python-daemon (>=3.0.1)
Requires-Dist: python-semantic-release (>=9.14.0)
Requires-Dist: pyyaml (>=6.0.2)
Requires-Dist: requests (>=2.31.0)
Requires-Dist: rich (>=13.7.0)
Requires-Dist: sqlalchemy (>=2.0.23)
Requires-Dist: structlog (>=24.1.0)
